{
    "name": "Face E2E Reports",
    "date": 1692964961468,
    "dateH": "8/25/2023, 12:02:41 PM",
    "duration": 143801,
    "durationH": "2m 24s",
    "cwd": "/home/runner/work/face-mask/face-mask/packages/e2e",
    "outputFile": "playwright-report/index.html",
    "outputDir": "playwright-report",
    "metadata": {},
    "system": [
        {
            "cpu": {
                "color": "#117DBB",
                "count": 2,
                "model": "Intel(R) Xeon(R) Platinum 8171M CPU @ 2.60GHz",
                "speed": 2095
            },
            "mem": {
                "color": "#8B12AE",
                "total": 7268679680
            },
            "arch": "x64",
            "platform": "linux",
            "release": "5.15.0-1041-azure",
            "type": "Linux",
            "version": "#48-Ubuntu SMP Tue Jun 20 20:34:08 UTC 2023",
            "uptime": 454.5,
            "hostname": "fv-az404-135",
            "pid": 2945,
            "node": "16.20.2",
            "v8": "9.4.146.26-node.26",
            "timestampStart": 1692964961468,
            "ticks": [
                {
                    "cpu": {
                        "percent": 59.32
                    },
                    "mem": {
                        "free": 5496098816
                    },
                    "timestamp": 1692964965088
                },
                {
                    "cpu": {
                        "percent": 27.27
                    },
                    "mem": {
                        "free": 5413040128
                    },
                    "timestamp": 1692964967089
                },
                {
                    "cpu": {
                        "percent": 3.02
                    },
                    "mem": {
                        "free": 5408845824
                    },
                    "timestamp": 1692964969090
                },
                {
                    "cpu": {
                        "percent": 4
                    },
                    "mem": {
                        "free": 5408854016
                    },
                    "timestamp": 1692964971090
                },
                {
                    "cpu": {
                        "percent": 4
                    },
                    "mem": {
                        "free": 5399212032
                    },
                    "timestamp": 1692964973093
                },
                {
                    "cpu": {
                        "percent": 2.51
                    },
                    "mem": {
                        "free": 5399244800
                    },
                    "timestamp": 1692964975093
                },
                {
                    "cpu": {
                        "percent": 8.06
                    },
                    "mem": {
                        "free": 5404983296
                    },
                    "timestamp": 1692964977094
                },
                {
                    "cpu": {
                        "percent": 5.53
                    },
                    "mem": {
                        "free": 5404401664
                    },
                    "timestamp": 1692964979094
                },
                {
                    "cpu": {
                        "percent": 3
                    },
                    "mem": {
                        "free": 5404401664
                    },
                    "timestamp": 1692964981095
                },
                {
                    "cpu": {
                        "percent": 12.02
                    },
                    "mem": {
                        "free": 5409206272
                    },
                    "timestamp": 1692964983095
                },
                {
                    "cpu": {
                        "percent": 10.73
                    },
                    "mem": {
                        "free": 5409353728
                    },
                    "timestamp": 1692964985097
                },
                {
                    "cpu": {
                        "percent": 2.5
                    },
                    "mem": {
                        "free": 5409112064
                    },
                    "timestamp": 1692964987097
                },
                {
                    "cpu": {
                        "percent": 2.02
                    },
                    "mem": {
                        "free": 5409124352
                    },
                    "timestamp": 1692964989097
                },
                {
                    "cpu": {
                        "percent": 3.98
                    },
                    "mem": {
                        "free": 5409198080
                    },
                    "timestamp": 1692964991098
                },
                {
                    "cpu": {
                        "percent": 39
                    },
                    "mem": {
                        "free": 5434286080
                    },
                    "timestamp": 1692964993098
                },
                {
                    "cpu": {
                        "percent": 2.51
                    },
                    "mem": {
                        "free": 5434130432
                    },
                    "timestamp": 1692964995100
                },
                {
                    "cpu": {
                        "percent": 16
                    },
                    "mem": {
                        "free": 5582581760
                    },
                    "timestamp": 1692964997100
                },
                {
                    "cpu": {
                        "percent": 21.94
                    },
                    "mem": {
                        "free": 5596688384
                    },
                    "timestamp": 1692964997833
                }
            ],
            "workers": 1,
            "jobs": [],
            "cwd": "/home/runner/work/face-mask/face-mask/packages/e2e",
            "configFile": "cmd/config/playwright.config.ts",
            "playwright": "1.37.0",
            "monocart": "1.7.4",
            "testDir": "src",
            "outputFile": "test-results/POLYGON_parallel/index.html",
            "outputDir": "test-results/POLYGON_parallel",
            "timestampEnd": 1692964997853
        },
        {
            "cpu": {
                "color": "#117DBB",
                "count": 2,
                "model": "Intel(R) Xeon(R) Platinum 8171M CPU @ 2.60GHz",
                "speed": 2095
            },
            "mem": {
                "color": "#8B12AE",
                "total": 7268679680
            },
            "arch": "x64",
            "platform": "linux",
            "release": "5.15.0-1041-azure",
            "type": "Linux",
            "version": "#48-Ubuntu SMP Tue Jun 20 20:34:08 UTC 2023",
            "uptime": 454.5,
            "hostname": "fv-az404-135",
            "pid": 2950,
            "node": "16.20.2",
            "v8": "9.4.146.26-node.26",
            "timestampStart": 1692964961468,
            "ticks": [
                {
                    "cpu": {
                        "percent": 59.55
                    },
                    "mem": {
                        "free": 5496098816
                    },
                    "timestamp": 1692964965090
                },
                {
                    "cpu": {
                        "percent": 27.14
                    },
                    "mem": {
                        "free": 5413040128
                    },
                    "timestamp": 1692964967090
                },
                {
                    "cpu": {
                        "percent": 3.03
                    },
                    "mem": {
                        "free": 5408845824
                    },
                    "timestamp": 1692964969091
                },
                {
                    "cpu": {
                        "percent": 3.98
                    },
                    "mem": {
                        "free": 5408854016
                    },
                    "timestamp": 1692964971092
                },
                {
                    "cpu": {
                        "percent": 4
                    },
                    "mem": {
                        "free": 5399212032
                    },
                    "timestamp": 1692964973093
                },
                {
                    "cpu": {
                        "percent": 2.51
                    },
                    "mem": {
                        "free": 5399244800
                    },
                    "timestamp": 1692964975094
                },
                {
                    "cpu": {
                        "percent": 8.06
                    },
                    "mem": {
                        "free": 5404983296
                    },
                    "timestamp": 1692964977094
                },
                {
                    "cpu": {
                        "percent": 5.5
                    },
                    "mem": {
                        "free": 5404401664
                    },
                    "timestamp": 1692964979096
                },
                {
                    "cpu": {
                        "percent": 3
                    },
                    "mem": {
                        "free": 5404401664
                    },
                    "timestamp": 1692964981097
                },
                {
                    "cpu": {
                        "percent": 12.02
                    },
                    "mem": {
                        "free": 5409206272
                    },
                    "timestamp": 1692964983098
                },
                {
                    "cpu": {
                        "percent": 10.67
                    },
                    "mem": {
                        "free": 5409353728
                    },
                    "timestamp": 1692964985099
                },
                {
                    "cpu": {
                        "percent": 2.5
                    },
                    "mem": {
                        "free": 5409112064
                    },
                    "timestamp": 1692964987102
                },
                {
                    "cpu": {
                        "percent": 2.03
                    },
                    "mem": {
                        "free": 5409124352
                    },
                    "timestamp": 1692964989102
                },
                {
                    "cpu": {
                        "percent": 4
                    },
                    "mem": {
                        "free": 5409198080
                    },
                    "timestamp": 1692964991102
                },
                {
                    "cpu": {
                        "percent": 39.5
                    },
                    "mem": {
                        "free": 5434286080
                    },
                    "timestamp": 1692964993103
                },
                {
                    "cpu": {
                        "percent": 2.99
                    },
                    "mem": {
                        "free": 5434130432
                    },
                    "timestamp": 1692964995105
                },
                {
                    "cpu": {
                        "percent": 16.34
                    },
                    "mem": {
                        "free": 5582581760
                    },
                    "timestamp": 1692964997106
                },
                {
                    "cpu": {
                        "percent": 23.86
                    },
                    "mem": {
                        "free": 5602623488
                    },
                    "timestamp": 1692964997857
                }
            ],
            "workers": 1,
            "jobs": [],
            "cwd": "/home/runner/work/face-mask/face-mask/packages/e2e",
            "configFile": "cmd/config/playwright.config.ts",
            "playwright": "1.37.0",
            "monocart": "1.7.4",
            "testDir": "src",
            "outputFile": "test-results/KLAYTN_parallel/index.html",
            "outputDir": "test-results/KLAYTN_parallel",
            "timestampEnd": 1692964997868
        },
        {
            "cpu": {
                "color": "#117DBB",
                "count": 2,
                "model": "Intel(R) Xeon(R) Platinum 8171M CPU @ 2.60GHz",
                "speed": 2095
            },
            "mem": {
                "color": "#8B12AE",
                "total": 7268679680
            },
            "arch": "x64",
            "platform": "linux",
            "release": "5.15.0-1041-azure",
            "type": "Linux",
            "version": "#48-Ubuntu SMP Tue Jun 20 20:34:08 UTC 2023",
            "uptime": 492.63,
            "hostname": "fv-az404-135",
            "pid": 3306,
            "node": "16.20.2",
            "v8": "9.4.146.26-node.26",
            "timestampStart": 1692964999602,
            "ticks": [
                {
                    "cpu": {
                        "percent": 78.39
                    },
                    "mem": {
                        "free": 5563473920
                    },
                    "timestamp": 1692965001628
                },
                {
                    "cpu": {
                        "percent": 17.19
                    },
                    "mem": {
                        "free": 5527384064
                    },
                    "timestamp": 1692965003637
                },
                {
                    "cpu": {
                        "percent": 3.5
                    },
                    "mem": {
                        "free": 5527384064
                    },
                    "timestamp": 1692965005638
                },
                {
                    "cpu": {
                        "percent": 3.54
                    },
                    "mem": {
                        "free": 5519159296
                    },
                    "timestamp": 1692965007639
                },
                {
                    "cpu": {
                        "percent": 3.02
                    },
                    "mem": {
                        "free": 5517533184
                    },
                    "timestamp": 1692965009639
                },
                {
                    "cpu": {
                        "percent": 2.01
                    },
                    "mem": {
                        "free": 5517533184
                    },
                    "timestamp": 1692965011640
                },
                {
                    "cpu": {
                        "percent": 3.02
                    },
                    "mem": {
                        "free": 5517541376
                    },
                    "timestamp": 1692965013641
                },
                {
                    "cpu": {
                        "percent": 4.04
                    },
                    "mem": {
                        "free": 5517557760
                    },
                    "timestamp": 1692965015641
                },
                {
                    "cpu": {
                        "percent": 11.17
                    },
                    "mem": {
                        "free": 5542559744
                    },
                    "timestamp": 1692965017643
                },
                {
                    "cpu": {
                        "percent": 2.97
                    },
                    "mem": {
                        "free": 5542563840
                    },
                    "timestamp": 1692965019644
                },
                {
                    "cpu": {
                        "percent": 2.51
                    },
                    "mem": {
                        "free": 5542346752
                    },
                    "timestamp": 1692965021645
                },
                {
                    "cpu": {
                        "percent": 7.07
                    },
                    "mem": {
                        "free": 5544153088
                    },
                    "timestamp": 1692965023646
                },
                {
                    "cpu": {
                        "percent": 13
                    },
                    "mem": {
                        "free": 5580832768
                    },
                    "timestamp": 1692965025647
                },
                {
                    "cpu": {
                        "percent": 2.03
                    },
                    "mem": {
                        "free": 5581451264
                    },
                    "timestamp": 1692965027647
                },
                {
                    "cpu": {
                        "percent": 2.97
                    },
                    "mem": {
                        "free": 5581709312
                    },
                    "timestamp": 1692965029649
                },
                {
                    "cpu": {
                        "percent": 5.03
                    },
                    "mem": {
                        "free": 5590003712
                    },
                    "timestamp": 1692965031651
                },
                {
                    "cpu": {
                        "percent": 2.51
                    },
                    "mem": {
                        "free": 5590904832
                    },
                    "timestamp": 1692965033651
                },
                {
                    "cpu": {
                        "percent": 5.53
                    },
                    "mem": {
                        "free": 5818085376
                    },
                    "timestamp": 1692965033733
                }
            ],
            "workers": 1,
            "jobs": [],
            "cwd": "/home/runner/work/face-mask/face-mask/packages/e2e",
            "configFile": "cmd/config/playwright.config.ts",
            "playwright": "1.37.0",
            "monocart": "1.7.4",
            "testDir": "src",
            "outputFile": "test-results/HOME_VERSE_parallel/index.html",
            "outputDir": "test-results/HOME_VERSE_parallel",
            "timestampEnd": 1692965033742
        },
        {
            "cpu": {
                "color": "#117DBB",
                "count": 2,
                "model": "Intel(R) Xeon(R) Platinum 8171M CPU @ 2.60GHz",
                "speed": 2095
            },
            "mem": {
                "color": "#8B12AE",
                "total": 7268679680
            },
            "arch": "x64",
            "platform": "linux",
            "release": "5.15.0-1041-azure",
            "type": "Linux",
            "version": "#48-Ubuntu SMP Tue Jun 20 20:34:08 UTC 2023",
            "uptime": 492.61,
            "hostname": "fv-az404-135",
            "pid": 3301,
            "node": "16.20.2",
            "v8": "9.4.146.26-node.26",
            "timestampStart": 1692964999586,
            "ticks": [
                {
                    "cpu": {
                        "percent": 78
                    },
                    "mem": {
                        "free": 5563473920
                    },
                    "timestamp": 1692965001620
                },
                {
                    "cpu": {
                        "percent": 18.75
                    },
                    "mem": {
                        "free": 5527384064
                    },
                    "timestamp": 1692965003622
                },
                {
                    "cpu": {
                        "percent": 3.52
                    },
                    "mem": {
                        "free": 5527384064
                    },
                    "timestamp": 1692965005622
                },
                {
                    "cpu": {
                        "percent": 3.54
                    },
                    "mem": {
                        "free": 5519990784
                    },
                    "timestamp": 1692965007624
                },
                {
                    "cpu": {
                        "percent": 2.99
                    },
                    "mem": {
                        "free": 5517533184
                    },
                    "timestamp": 1692965009625
                },
                {
                    "cpu": {
                        "percent": 2.01
                    },
                    "mem": {
                        "free": 5517533184
                    },
                    "timestamp": 1692965011625
                },
                {
                    "cpu": {
                        "percent": 3.02
                    },
                    "mem": {
                        "free": 5517541376
                    },
                    "timestamp": 1692965013625
                },
                {
                    "cpu": {
                        "percent": 4.02
                    },
                    "mem": {
                        "free": 5517557760
                    },
                    "timestamp": 1692965015625
                },
                {
                    "cpu": {
                        "percent": 11.06
                    },
                    "mem": {
                        "free": 5542559744
                    },
                    "timestamp": 1692965017625
                },
                {
                    "cpu": {
                        "percent": 3.48
                    },
                    "mem": {
                        "free": 5542563840
                    },
                    "timestamp": 1692965019625
                },
                {
                    "cpu": {
                        "percent": 2.51
                    },
                    "mem": {
                        "free": 5542346752
                    },
                    "timestamp": 1692965021625
                },
                {
                    "cpu": {
                        "percent": 7.07
                    },
                    "mem": {
                        "free": 5544153088
                    },
                    "timestamp": 1692965023625
                },
                {
                    "cpu": {
                        "percent": 12
                    },
                    "mem": {
                        "free": 5579644928
                    },
                    "timestamp": 1692965025626
                },
                {
                    "cpu": {
                        "percent": 2.03
                    },
                    "mem": {
                        "free": 5581451264
                    },
                    "timestamp": 1692965027627
                },
                {
                    "cpu": {
                        "percent": 2.5
                    },
                    "mem": {
                        "free": 5581709312
                    },
                    "timestamp": 1692965029628
                },
                {
                    "cpu": {
                        "percent": 5.03
                    },
                    "mem": {
                        "free": 5590003712
                    },
                    "timestamp": 1692965031629
                },
                {
                    "cpu": {
                        "percent": 3.02
                    },
                    "mem": {
                        "free": 5590904832
                    },
                    "timestamp": 1692965033631
                },
                {
                    "cpu": {
                        "percent": 2.01
                    },
                    "mem": {
                        "free": 5590904832
                    },
                    "timestamp": 1692965033662
                }
            ],
            "workers": 1,
            "jobs": [],
            "cwd": "/home/runner/work/face-mask/face-mask/packages/e2e",
            "configFile": "cmd/config/playwright.config.ts",
            "playwright": "1.37.0",
            "monocart": "1.7.4",
            "testDir": "src",
            "outputFile": "test-results/OASYS_parallel/index.html",
            "outputDir": "test-results/OASYS_parallel",
            "timestampEnd": 1692965033671
        },
        {
            "cpu": {
                "color": "#117DBB",
                "count": 2,
                "model": "Intel(R) Xeon(R) Platinum 8171M CPU @ 2.60GHz",
                "speed": 2095
            },
            "mem": {
                "color": "#8B12AE",
                "total": 7268679680
            },
            "arch": "x64",
            "platform": "linux",
            "release": "5.15.0-1041-azure",
            "type": "Linux",
            "version": "#48-Ubuntu SMP Tue Jun 20 20:34:08 UTC 2023",
            "uptime": 528.34,
            "hostname": "fv-az404-135",
            "pid": 3660,
            "node": "16.20.2",
            "v8": "9.4.146.26-node.26",
            "timestampStart": 1692965035317,
            "ticks": [
                {
                    "cpu": {
                        "percent": 80.6
                    },
                    "mem": {
                        "free": 5551443968
                    },
                    "timestamp": 1692965037351
                },
                {
                    "cpu": {
                        "percent": 12.44
                    },
                    "mem": {
                        "free": 5513945088
                    },
                    "timestamp": 1692965039357
                },
                {
                    "cpu": {
                        "percent": 2.53
                    },
                    "mem": {
                        "free": 5513945088
                    },
                    "timestamp": 1692965041358
                },
                {
                    "cpu": {
                        "percent": 3
                    },
                    "mem": {
                        "free": 5506109440
                    },
                    "timestamp": 1692965043359
                },
                {
                    "cpu": {
                        "percent": 2.51
                    },
                    "mem": {
                        "free": 5504307200
                    },
                    "timestamp": 1692965045360
                },
                {
                    "cpu": {
                        "percent": 1.52
                    },
                    "mem": {
                        "free": 5504327680
                    },
                    "timestamp": 1692965047362
                },
                {
                    "cpu": {
                        "percent": 3
                    },
                    "mem": {
                        "free": 5504339968
                    },
                    "timestamp": 1692965049362
                },
                {
                    "cpu": {
                        "percent": 2.01
                    },
                    "mem": {
                        "free": 5504339968
                    },
                    "timestamp": 1692965051362
                },
                {
                    "cpu": {
                        "percent": 12.56
                    },
                    "mem": {
                        "free": 5559693312
                    },
                    "timestamp": 1692965053362
                },
                {
                    "cpu": {
                        "percent": 2.97
                    },
                    "mem": {
                        "free": 5559693312
                    },
                    "timestamp": 1692965055363
                },
                {
                    "cpu": {
                        "percent": 4
                    },
                    "mem": {
                        "free": 5559701504
                    },
                    "timestamp": 1692965057365
                },
                {
                    "cpu": {
                        "percent": 7.5
                    },
                    "mem": {
                        "free": 5574238208
                    },
                    "timestamp": 1692965059366
                },
                {
                    "cpu": {
                        "percent": 6.44
                    },
                    "mem": {
                        "free": 5574725632
                    },
                    "timestamp": 1692965061388
                },
                {
                    "cpu": {
                        "percent": 2.54
                    },
                    "mem": {
                        "free": 5574983680
                    },
                    "timestamp": 1692965063389
                },
                {
                    "cpu": {
                        "percent": 2.01
                    },
                    "mem": {
                        "free": 5574725632
                    },
                    "timestamp": 1692965065389
                },
                {
                    "cpu": {
                        "percent": 9.05
                    },
                    "mem": {
                        "free": 5586608128
                    },
                    "timestamp": 1692965067390
                },
                {
                    "cpu": {
                        "percent": 9.5
                    },
                    "mem": {
                        "free": 5833986048
                    },
                    "timestamp": 1692965069392
                },
                {
                    "cpu": {
                        "percent": 9.05
                    },
                    "mem": {
                        "free": 5829480448
                    },
                    "timestamp": 1692965069411
                }
            ],
            "workers": 1,
            "jobs": [],
            "cwd": "/home/runner/work/face-mask/face-mask/packages/e2e",
            "configFile": "cmd/config/playwright.config.ts",
            "playwright": "1.37.0",
            "monocart": "1.7.4",
            "testDir": "src",
            "outputFile": "test-results/POLYGON_serial/index.html",
            "outputDir": "test-results/POLYGON_serial",
            "timestampEnd": 1692965069418
        },
        {
            "cpu": {
                "color": "#117DBB",
                "count": 2,
                "model": "Intel(R) Xeon(R) Platinum 8171M CPU @ 2.60GHz",
                "speed": 2095
            },
            "mem": {
                "color": "#8B12AE",
                "total": 7268679680
            },
            "arch": "x64",
            "platform": "linux",
            "release": "5.15.0-1041-azure",
            "type": "Linux",
            "version": "#48-Ubuntu SMP Tue Jun 20 20:34:08 UTC 2023",
            "uptime": 528.34,
            "hostname": "fv-az404-135",
            "pid": 3666,
            "node": "16.20.2",
            "v8": "9.4.146.26-node.26",
            "timestampStart": 1692965035316,
            "ticks": [
                {
                    "cpu": {
                        "percent": 80.5
                    },
                    "mem": {
                        "free": 5551443968
                    },
                    "timestamp": 1692965037346
                },
                {
                    "cpu": {
                        "percent": 13.43
                    },
                    "mem": {
                        "free": 5513945088
                    },
                    "timestamp": 1692965039347
                },
                {
                    "cpu": {
                        "percent": 2.53
                    },
                    "mem": {
                        "free": 5513945088
                    },
                    "timestamp": 1692965041349
                },
                {
                    "cpu": {
                        "percent": 3.02
                    },
                    "mem": {
                        "free": 5506109440
                    },
                    "timestamp": 1692965043351
                },
                {
                    "cpu": {
                        "percent": 2.51
                    },
                    "mem": {
                        "free": 5504307200
                    },
                    "timestamp": 1692965045353
                },
                {
                    "cpu": {
                        "percent": 1.52
                    },
                    "mem": {
                        "free": 5504327680
                    },
                    "timestamp": 1692965047354
                },
                {
                    "cpu": {
                        "percent": 2.99
                    },
                    "mem": {
                        "free": 5504339968
                    },
                    "timestamp": 1692965049355
                },
                {
                    "cpu": {
                        "percent": 2.02
                    },
                    "mem": {
                        "free": 5504339968
                    },
                    "timestamp": 1692965051357
                },
                {
                    "cpu": {
                        "percent": 12.69
                    },
                    "mem": {
                        "free": 5559693312
                    },
                    "timestamp": 1692965053357
                },
                {
                    "cpu": {
                        "percent": 2.99
                    },
                    "mem": {
                        "free": 5559693312
                    },
                    "timestamp": 1692965055358
                },
                {
                    "cpu": {
                        "percent": 4.02
                    },
                    "mem": {
                        "free": 5559701504
                    },
                    "timestamp": 1692965057360
                },
                {
                    "cpu": {
                        "percent": 7.54
                    },
                    "mem": {
                        "free": 5574238208
                    },
                    "timestamp": 1692965059361
                },
                {
                    "cpu": {
                        "percent": 3.54
                    },
                    "mem": {
                        "free": 5576818688
                    },
                    "timestamp": 1692965061361
                },
                {
                    "cpu": {
                        "percent": 2.54
                    },
                    "mem": {
                        "free": 5574983680
                    },
                    "timestamp": 1692965063363
                },
                {
                    "cpu": {
                        "percent": 2.01
                    },
                    "mem": {
                        "free": 5574725632
                    },
                    "timestamp": 1692965065363
                },
                {
                    "cpu": {
                        "percent": 9.05
                    },
                    "mem": {
                        "free": 5586608128
                    },
                    "timestamp": 1692965067364
                },
                {
                    "cpu": {
                        "percent": 4.02
                    },
                    "mem": {
                        "free": 5593112576
                    },
                    "timestamp": 1692965069311
                }
            ],
            "workers": 1,
            "jobs": [],
            "cwd": "/home/runner/work/face-mask/face-mask/packages/e2e",
            "configFile": "cmd/config/playwright.config.ts",
            "playwright": "1.37.0",
            "monocart": "1.7.4",
            "testDir": "src",
            "outputFile": "test-results/KLAYTN_serial/index.html",
            "outputDir": "test-results/KLAYTN_serial",
            "timestampEnd": 1692965069320
        },
        {
            "cpu": {
                "color": "#117DBB",
                "count": 2,
                "model": "Intel(R) Xeon(R) Platinum 8171M CPU @ 2.60GHz",
                "speed": 2095
            },
            "mem": {
                "color": "#8B12AE",
                "total": 7268679680
            },
            "arch": "x64",
            "platform": "linux",
            "release": "5.15.0-1041-azure",
            "type": "Linux",
            "version": "#48-Ubuntu SMP Tue Jun 20 20:34:08 UTC 2023",
            "uptime": 563.95,
            "hostname": "fv-az404-135",
            "pid": 4011,
            "node": "16.20.2",
            "v8": "9.4.146.26-node.26",
            "timestampStart": 1692965070918,
            "ticks": [
                {
                    "cpu": {
                        "percent": 71.72
                    },
                    "mem": {
                        "free": 5571088384
                    },
                    "timestamp": 1692965072950
                },
                {
                    "cpu": {
                        "percent": 22.39
                    },
                    "mem": {
                        "free": 5522341888
                    },
                    "timestamp": 1692965074952
                },
                {
                    "cpu": {
                        "percent": 3.03
                    },
                    "mem": {
                        "free": 5522124800
                    },
                    "timestamp": 1692965076953
                },
                {
                    "cpu": {
                        "percent": 4
                    },
                    "mem": {
                        "free": 5516042240
                    },
                    "timestamp": 1692965078955
                },
                {
                    "cpu": {
                        "percent": 2.02
                    },
                    "mem": {
                        "free": 5512589312
                    },
                    "timestamp": 1692965080956
                },
                {
                    "cpu": {
                        "percent": 3.5
                    },
                    "mem": {
                        "free": 5512589312
                    },
                    "timestamp": 1692965082958
                },
                {
                    "cpu": {
                        "percent": 3.52
                    },
                    "mem": {
                        "free": 5512589312
                    },
                    "timestamp": 1692965084959
                },
                {
                    "cpu": {
                        "percent": 2.5
                    },
                    "mem": {
                        "free": 5512597504
                    },
                    "timestamp": 1692965086960
                },
                {
                    "cpu": {
                        "percent": 22.89
                    },
                    "mem": {
                        "free": 5560393728
                    },
                    "timestamp": 1692965088961
                },
                {
                    "cpu": {
                        "percent": 2.03
                    },
                    "mem": {
                        "free": 5560524800
                    },
                    "timestamp": 1692965090961
                },
                {
                    "cpu": {
                        "percent": 2.54
                    },
                    "mem": {
                        "free": 5559533568
                    },
                    "timestamp": 1692965092962
                },
                {
                    "cpu": {
                        "percent": 8.08
                    },
                    "mem": {
                        "free": 5572591616
                    },
                    "timestamp": 1692965094964
                },
                {
                    "cpu": {
                        "percent": 3.06
                    },
                    "mem": {
                        "free": 5574950912
                    },
                    "timestamp": 1692965096965
                },
                {
                    "cpu": {
                        "percent": 2.5
                    },
                    "mem": {
                        "free": 5575008256
                    },
                    "timestamp": 1692965098967
                },
                {
                    "cpu": {
                        "percent": 3.98
                    },
                    "mem": {
                        "free": 5575016448
                    },
                    "timestamp": 1692965100968
                },
                {
                    "cpu": {
                        "percent": 8.54
                    },
                    "mem": {
                        "free": 5593866240
                    },
                    "timestamp": 1692965102969
                },
                {
                    "cpu": {
                        "percent": 2.5
                    },
                    "mem": {
                        "free": 5596205056
                    },
                    "timestamp": 1692965104971
                },
                {
                    "cpu": {
                        "percent": 2.01
                    },
                    "mem": {
                        "free": 5596205056
                    },
                    "timestamp": 1692965105075
                }
            ],
            "workers": 1,
            "jobs": [],
            "cwd": "/home/runner/work/face-mask/face-mask/packages/e2e",
            "configFile": "cmd/config/playwright.config.ts",
            "playwright": "1.37.0",
            "monocart": "1.7.4",
            "testDir": "src",
            "outputFile": "test-results/HOME_VERSE_serial/index.html",
            "outputDir": "test-results/HOME_VERSE_serial",
            "timestampEnd": 1692965105086
        },
        {
            "cpu": {
                "color": "#117DBB",
                "count": 2,
                "model": "Intel(R) Xeon(R) Platinum 8171M CPU @ 2.60GHz",
                "speed": 2095
            },
            "mem": {
                "color": "#8B12AE",
                "total": 7268679680
            },
            "arch": "x64",
            "platform": "linux",
            "release": "5.15.0-1041-azure",
            "type": "Linux",
            "version": "#48-Ubuntu SMP Tue Jun 20 20:34:08 UTC 2023",
            "uptime": 564.03,
            "hostname": "fv-az404-135",
            "pid": 4027,
            "node": "16.20.2",
            "v8": "9.4.146.26-node.26",
            "timestampStart": 1692965071005,
            "ticks": [
                {
                    "cpu": {
                        "percent": 73.85
                    },
                    "mem": {
                        "free": 5559480320
                    },
                    "timestamp": 1692965073042
                },
                {
                    "cpu": {
                        "percent": 20.5
                    },
                    "mem": {
                        "free": 5522124800
                    },
                    "timestamp": 1692965075043
                },
                {
                    "cpu": {
                        "percent": 3.02
                    },
                    "mem": {
                        "free": 5522124800
                    },
                    "timestamp": 1692965077045
                },
                {
                    "cpu": {
                        "percent": 4
                    },
                    "mem": {
                        "free": 5515329536
                    },
                    "timestamp": 1692965079046
                },
                {
                    "cpu": {
                        "percent": 2.51
                    },
                    "mem": {
                        "free": 5512589312
                    },
                    "timestamp": 1692965081047
                },
                {
                    "cpu": {
                        "percent": 3.5
                    },
                    "mem": {
                        "free": 5512589312
                    },
                    "timestamp": 1692965083048
                },
                {
                    "cpu": {
                        "percent": 3.02
                    },
                    "mem": {
                        "free": 5512589312
                    },
                    "timestamp": 1692965085048
                },
                {
                    "cpu": {
                        "percent": 3
                    },
                    "mem": {
                        "free": 5512597504
                    },
                    "timestamp": 1692965087048
                },
                {
                    "cpu": {
                        "percent": 22.77
                    },
                    "mem": {
                        "free": 5560393728
                    },
                    "timestamp": 1692965089050
                },
                {
                    "cpu": {
                        "percent": 2.02
                    },
                    "mem": {
                        "free": 5560524800
                    },
                    "timestamp": 1692965091050
                },
                {
                    "cpu": {
                        "percent": 3.02
                    },
                    "mem": {
                        "free": 5559533568
                    },
                    "timestamp": 1692965093052
                },
                {
                    "cpu": {
                        "percent": 8.04
                    },
                    "mem": {
                        "free": 5572591616
                    },
                    "timestamp": 1692965095053
                },
                {
                    "cpu": {
                        "percent": 3.05
                    },
                    "mem": {
                        "free": 5574950912
                    },
                    "timestamp": 1692965097053
                },
                {
                    "cpu": {
                        "percent": 2.51
                    },
                    "mem": {
                        "free": 5575008256
                    },
                    "timestamp": 1692965099054
                },
                {
                    "cpu": {
                        "percent": 3.98
                    },
                    "mem": {
                        "free": 5575016448
                    },
                    "timestamp": 1692965101054
                },
                {
                    "cpu": {
                        "percent": 7.96
                    },
                    "mem": {
                        "free": 5593866240
                    },
                    "timestamp": 1692965103056
                },
                {
                    "cpu": {
                        "percent": 3
                    },
                    "mem": {
                        "free": 5596205056
                    },
                    "timestamp": 1692965105057
                },
                {
                    "cpu": {
                        "percent": 7.04
                    },
                    "mem": {
                        "free": 5836197888
                    },
                    "timestamp": 1692965105257
                }
            ],
            "workers": 1,
            "jobs": [],
            "cwd": "/home/runner/work/face-mask/face-mask/packages/e2e",
            "configFile": "cmd/config/playwright.config.ts",
            "playwright": "1.37.0",
            "monocart": "1.7.4",
            "testDir": "src",
            "outputFile": "test-results/OASYS_serial/index.html",
            "outputDir": "test-results/OASYS_serial",
            "timestampEnd": 1692965105269
        }
    ],
    "artifacts": [],
    "trends": [],
    "columns": [
        {
            "id": "caseType",
            "name": "",
            "width": 36,
            "sortable": false,
            "align": "center",
            "formatter": "iconCaseType",
            "detailed": false
        },
        {
            "id": "title",
            "name": "Title",
            "searchable": true,
            "width": 350,
            "maxWidth": 1230,
            "detailed": false
        },
        {
            "id": "type",
            "name": "Type",
            "width": 50,
            "sortable": false,
            "align": "center",
            "formatter": "iconType",
            "detailed": false
        },
        {
            "id": "duration",
            "name": "Duration",
            "align": "right",
            "sortAsc": false,
            "formatter": "duration",
            "detailed": false
        },
        {
            "id": "errors",
            "name": "Errors",
            "width": 60,
            "align": "center",
            "comparer": "errors",
            "formatter": "errors",
            "detailed": false
        },
        {
            "id": "logs",
            "name": "Logs",
            "width": 60,
            "align": "center",
            "comparer": "logs",
            "formatter": "logs",
            "detailed": false
        },
        {
            "id": "annotations",
            "name": "Annotations",
            "width": 100,
            "markdown": true,
            "searchable": true,
            "comparer": "annotations",
            "formatter": "annotations",
            "detailed": false
        },
        {
            "id": "attachments",
            "name": "Attachments",
            "width": 100,
            "align": "center",
            "formatter": "attachments",
            "detailed": false
        },
        {
            "id": "status",
            "name": "Status",
            "align": "center",
            "detailed": false
        },
        {
            "id": "expectedStatus",
            "name": "Expected",
            "align": "center",
            "detailed": false
        },
        {
            "id": "outcome",
            "name": "Outcome",
            "align": "center",
            "width": 85,
            "detailed": false
        },
        {
            "id": "retry",
            "name": "Retry",
            "align": "center",
            "width": 50,
            "detailed": false
        },
        {
            "id": "location",
            "name": "Location",
            "classMap": "mcr-location",
            "width": 200,
            "maxWidth": 1981,
            "detailed": false
        }
    ],
    "rows": [
        {
            "title": "fv-az404-135",
            "type": "suite",
            "suiteType": "shard",
            "caseNum": 0,
            "subs": []
        },
        {
            "title": "fv-az404-135",
            "type": "suite",
            "suiteType": "shard",
            "caseNum": 0,
            "subs": []
        },
        {
            "title": "fv-az404-135",
            "type": "suite",
            "suiteType": "shard",
            "caseNum": 0,
            "subs": []
        },
        {
            "title": "fv-az404-135",
            "type": "suite",
            "suiteType": "shard",
            "caseNum": 0,
            "subs": []
        },
        {
            "title": "fv-az404-135",
            "type": "suite",
            "suiteType": "shard",
            "caseNum": 0,
            "subs": []
        },
        {
            "title": "fv-az404-135",
            "type": "suite",
            "suiteType": "shard",
            "caseNum": 0,
            "subs": []
        },
        {
            "title": "fv-az404-135",
            "type": "suite",
            "suiteType": "shard",
            "caseNum": 0,
            "subs": []
        },
        {
            "title": "fv-az404-135",
            "type": "suite",
            "suiteType": "shard",
            "caseNum": 0,
            "subs": []
        }
    ],
    "formatters": {},
    "suiteTypes": [
        "project",
        "file",
        "describe",
        "shard"
    ],
    "caseTypes": [
        "passed",
        "flaky",
        "skipped",
        "failed"
    ],
    "traceViewerUrl": "https://trace.playwright.dev/?trace={traceUrl}",
    "tags": {},
    "summary": {
        "tests": {
            "name": "Tests",
            "value": 0,
            "nav": true,
            "id": "tests"
        },
        "passed": {
            "name": "Passed",
            "value": 0,
            "color": "green",
            "nav": true,
            "id": "passed",
            "percent": "0.0%"
        },
        "flaky": {
            "name": "Flaky",
            "value": 0,
            "color": "orange",
            "nav": true,
            "id": "flaky",
            "percent": "0.0%"
        },
        "skipped": {
            "name": "Skipped",
            "value": 0,
            "color": "gray",
            "nav": true,
            "id": "skipped",
            "percent": "0.0%"
        },
        "failed": {
            "name": "Failed",
            "value": 0,
            "color": "#d00",
            "nav": true,
            "id": "failed",
            "percent": "0.0%"
        },
        "steps": {
            "name": "Steps",
            "value": 0,
            "id": "steps"
        },
        "suites": {
            "name": "Suites",
            "value": 0,
            "id": "suites"
        },
        "projects": {
            "name": "Projects",
            "description": "Suite type is project",
            "value": 0,
            "id": "projects"
        },
        "files": {
            "name": "Files",
            "description": "Suite type is file",
            "value": 0,
            "id": "files"
        },
        "describes": {
            "name": "Describes",
            "description": "Suite type is describe",
            "value": 0,
            "id": "describes"
        },
        "shards": {
            "name": "Shards",
            "description": "Suite type is shard (only in shading mode)",
            "value": 8,
            "id": "shards"
        },
        "retries": {
            "name": "Retries",
            "value": 0,
            "id": "retries"
        },
        "errors": {
            "name": "Errors",
            "value": 0,
            "id": "errors"
        },
        "logs": {
            "name": "Logs",
            "value": 0,
            "id": "logs"
        },
        "attachments": {
            "name": "Attachments",
            "value": 0,
            "id": "attachments"
        }
    },
    "pieChart": {
        "ns": "mcr-pie",
        "width": 360,
        "height": 150,
        "margin": 10,
        "svg": "<svg viewBox=\"0 0 360 150\" width=\"100%\" height=\"100%\" xmlns=\"http://www.w3.org/2000/svg\"><circle cx=\"75\" cy=\"75\" r=\"65\" fill=\"#f5f5f5\" /><g transform=\"translate(160 10)\"><g class=\"mcr-pie-legend-passed\" transform=\"translate(0 0)\"><circle cx=\"10\" cy=\"16\" r=\"10\" fill=\"green\" opacity=\"0.8\" /><text x=\"30\" y=\"16\" alignment-baseline=\"middle\">Passed</text><text x=\"115\" y=\"16\" alignment-baseline=\"middle\" text-anchor=\"middle\">0</text><text x=\"190\" y=\"16\" alignment-baseline=\"middle\" text-anchor=\"end\">0.0%</text></g><g class=\"mcr-pie-legend-flaky\" transform=\"translate(0 32)\"><circle cx=\"10\" cy=\"16\" r=\"10\" fill=\"orange\" opacity=\"0.8\" /><text x=\"30\" y=\"16\" alignment-baseline=\"middle\">Flaky</text><text x=\"115\" y=\"16\" alignment-baseline=\"middle\" text-anchor=\"middle\">0</text><text x=\"190\" y=\"16\" alignment-baseline=\"middle\" text-anchor=\"end\">0.0%</text></g><g class=\"mcr-pie-legend-skipped\" transform=\"translate(0 64)\"><circle cx=\"10\" cy=\"16\" r=\"10\" fill=\"gray\" opacity=\"0.8\" /><text x=\"30\" y=\"16\" alignment-baseline=\"middle\">Skipped</text><text x=\"115\" y=\"16\" alignment-baseline=\"middle\" text-anchor=\"middle\">0</text><text x=\"190\" y=\"16\" alignment-baseline=\"middle\" text-anchor=\"end\">0.0%</text></g><g class=\"mcr-pie-legend-failed\" transform=\"translate(0 96)\"><circle cx=\"10\" cy=\"16\" r=\"10\" fill=\"#d00\" opacity=\"0.8\" /><text x=\"30\" y=\"16\" alignment-baseline=\"middle\">Failed</text><text x=\"115\" y=\"16\" alignment-baseline=\"middle\" text-anchor=\"middle\">0</text><text x=\"190\" y=\"16\" alignment-baseline=\"middle\" text-anchor=\"end\">0.0%</text></g></g></svg>"
    }
}
